Workbook

Sheet README
A1: Mercedes-Benz Financial Modelling Project | B1: Mercedes-Benz Financial Modelling Project | C1: Mercedes-Benz Financial Modelling Project | D1: Mercedes-Benz Financial Modelling Project | E1: Mercedes-Benz Financial Modelling Project | F1: Mercedes-Benz Financial Modelling Project | G1: Mercedes-Benz Financial Modelling Project | H1: Mercedes-Benz Financial Modelling Project
A3: Purpose | B3: Build a driver-based corporate finance / FP&A model for Mercedes-Benz, linking operating assumptions to revenue, margins, cash flow and valuation.
A5: Sheet | B5: What it does
A6: Assumptions | B6: Editable forecast drivers and valuation assumptions
A7: Historical | B7: Historical P&L and operating data placeholders
A8: Operating Model | B8: Cars sold, pricing, revenue and margin drivers
A9: P&L Forecast | B9: Forecast income statement
A10: Cash Flow | B10: Simplified free cash flow build
A11: DCF Valuation | B11: Enterprise value and equity value bridge
A12: Dashboard | B12: Key outputs and charts
A14: How to use
A15: 1 | B15: Replace yellow / blue-font assumption cells with researched Mercedes-Benz data.
A16: 2 | B16: Populate the Historical sheet for the last 3 years.
A17: 3 | B17: Review forecast drivers in Assumptions and Operating Model.
A18: 4 | B18: Check P&L, cash flow and DCF outputs.
A19: 5 | B19: Use the Dashboard for the final presentation / portfolio case study.

Sheet Assumptions
A1: Forecast Assumptions | B1: Forecast Assumptions | C1: Forecast Assumptions | D1: Forecast Assumptions | E1: Forecast Assumptions | F1: Forecast Assumptions | G1: Forecast Assumptions
A3: Metric | B3: Unit | C3: 2025A | D3: 2026E | E3: 2027E | F3: 2028E | G3: 2029E
A4: Vehicle volume growth | B4: % | C4: - | D4: -0.02 | E4: 0.03 | F4: 0.04 | G4: 0.04
A5: Vans revenue growth | B5: % | D5: -0.08 | E5: 0.03 | F5: 0.03 | G5: 0.02
A6: Average selling price growth | B6: % | C6: - | D6: 0 | E6: 0.02 | F6: 0.02 | G6: 0.02
A7: Financial services revenue growth | B7: % | C7: - | D7: 0 | E7: 0.02 | F7: 0.03 | G7: 0.03
A8: Gross margin | B8: % | C8: - | D8: 0.175 | E8: 0.185 | F8: 0.19 | G8: 0.195
A9: R&D as % of revenue | B9: % | C9: - | D9: 0.043 | E9: 0.042 | F9: 0.041 | G9: 0.04
A10: SG&A as % of revenue | B10: % | C10: - | D10: 0.092 | E10: 0.09 | F10: 0.088 | G10: 0.085
A11: Other items % Revenue | B11: % | D11: 0.01 | E11: 0.008 | F11: 0.006 | G11: 0.005
A12: Tax rate | B12: % | C12: - | D12: 0.28 | E12: 0.28 | F12: 0.28 | G12: 0.28
A13: D&A as % of revenue | B13: % | C13: - | D13: 0.054 | E13: 0.053 | F13: 0.052 | G13: 0.051
A14: Capex as % of revenue | B14: % | C14: - | D14: 0.07 | E14: 0.065 | F14: 0.06 | G14: 0.06
A15: NWC as % of revenue | B15: % | C15: - | D15: 0.145 | E15: 0.145 | F15: 0.145 | G15: 0.145
A16: RECONCILIATION % | B16: % | D16: -0.0432 | E16: -0.0432 | F16: -0.0432 | G16: -0.0432
A18: DCF Assumptions | B18: DCF Assumptions | C18: DCF Assumptions | D18: DCF Assumptions | E18: DCF Assumptions | F18: DCF Assumptions | G18: DCF Assumptions
A19: WACC | B19: 0.095
A20: Low Scenario WACC | B20: 0.105
A21: Low Scenario Terminal Growth | B21: 0.01
A22: High Scenario WACC | B22: 0.085
A23: High Scenario Terminal Growth | B23: 0.025
A26: Terminal growth | B26: 0.02
A27: Current share price (€) | B27: 41.28
A28: Target EV / EBITDA | B28: 4.5
A29: selected scenario | B29: Base
A30: Industrial Net Liquidity (€m) | B30: 32162
A31: Financial Services P/B (x) | B31: 1.47
A32: Financial Services Book Equity (€m) | B32: 12053
A33: Shares Outstanding (m) | B33: 962.904

Sheet Historical
A1: Historical Financials & Operating Data | B1: Historical Financials & Operating Data | C1: Historical Financials & Operating Data | D1: Historical Financials & Operating Data | E1: Historical Financials & Operating Data
A3: Metric | B3: Unit | C3: 2023A | D3: 2024A | E3: 2025A
A4: Cars sold | B4: 000 units | C4: 2044.051 | D4: 1983.403 | E4: 1801.291
A5: Average selling price | B5: €000 | C5: =C6/C4 -> 55.163007 | D5: =D6/D4 -> 54.33389 | E5: =E6/E4 -> 53.521058
A6: Mb cars revenue | B6: €m | C6: 112756 | D6: 107766 | E6: 96407 | G6: =E4*E5 -> 96407
A7: Financial services revenue | B7: €m | C7: 25571 | D7: 25083 | E7: 24625
A8: Total revenue | B8: €m | C8: 152393 | D8: 145594 | E8: 132214
A9: Gross profit | B9: €m | C9: 34999 | D9: 28576 | E9: 22333
A10: R&D | B10: €m | C10: 6230 | D10: 5580 | E10: 6055
A11: SG&A | B11: €m | C11: 12988 | D11: 12522 | E11: 12195
A12: EBIT | B12: €m | C12: 19660 | D12: 13600 | E12: 5820
A13: Net income | B13: €m | C13: 14531 | D13: 10409 | E13: 5331
A14: D&A | B14: €m | C14: 6663 | D14: 6772 | E14: 7223
A15: Capex | B15: €m | C15: 8213 | D15: 8665 | E15: 9742
A16: Net working capital | B16: €m | C16: =26126 + 6585 - 11625 -> 21086 | D16: =25786 + 6418 -10104 -> 22100 | E16: =23793+5354-9913 -> 19234
A17: Revenue Growth | B17: % | D17: =D8/C8-1 -> -0.04461491 | E17: =E8/D8-1 -> -0.091899391
A18: Gross Margin | B18: % | C18: =C9/C8 -> 0.22966278 | D18: =D9/D8 -> 0.19627182 | E18: =E9/E8 -> 0.16891555
A19: EBIT Margin | B19: % | C19: =C12/C8 -> 0.12900855 | D19: =D12/D8 -> 0.093410443 | E19: =E12/E8 -> 0.044019544
A20: Net Margin | B20: % | C20: =C13/C8 -> 0.095352149 | D20: =D13/D8 -> 0.071493331 | E20: =E13/E8 -> 0.040320995
A21: NWC % Revenue | B21: % | C21: =C16/C8 -> 0.13836594 | D21: =D16/D8 -> 0.15179197 | E21: =E16/E8 -> 0.14547627
A23: Note | B23: Replace these starter placeholders with figures from Mercedes-Benz annual reports / investor relations.
A24: Source | B24: https://group.mercedes-benz.com/investors/reports-news/annual-reports/
A25: Units | B25: All financial statement figures are intended to be €m unless stated otherwise.

Sheet Operating Model
A1: Operating Model | B1: Operating Model | C1: Operating Model | D1: Operating Model | E1: Operating Model | F1: Operating Model | G1: Operating Model
A3: Metric | B3: Unit | C3: 2025A | D3: 2026E | E3: 2027E | F3: 2028E | G3: 2029E
A4: Cars sold | B4: 000 units | C4: =Historical!E4 -> 1801.291 | D4: =C4*(1+D5) -> 1765.2652 | E4: =D4*(1+E5) -> 1818.2231 | F4: =E4*(1+F5) -> 1890.9521 | G4: =F4*(1+G5) -> 1966.5901
A5: Volume growth | B5: % | C5: - | D5: =Assumptions!D4 -> -0.02 | E5: =Assumptions!E4 -> 0.03 | F5: =Assumptions!F4 -> 0.04 | G5: =Assumptions!G4 -> 0.04
A6: Average selling price | B6: €000 | C6: =Historical!E5 -> 53.521058 | D6: =C6*(1+D7) -> 53.521058 | E6: =D6*(1+E7) -> 54.591479 | F6: =E6*(1+F7) -> 55.683309 | G6: =F6*(1+G7) -> 56.796975
A7: ASP growth | B7: % | C7: - | D7: =Assumptions!D6 -> 0 | E7: =Assumptions!E6 -> 0.02 | F7: =Assumptions!F6 -> 0.02 | G7: =Assumptions!G6 -> 0.02
A8: Automotive revenue | B8: €m | C8: =Historical!E6 -> 96407 | D8: =D4*D6 -> 94478.86 | E8: =E4*E6 -> 99259.49 | F8: =F4*F6 -> 105294.47 | G8: =G4*G6 -> 111696.37
A9: Vans revenue | B9: €m | C9: 17148 | D9: =C9*(1+Assumptions!D5) -> 15776.16 | E9: =D9*(1+Assumptions!E5) -> 16249.445 | F9: =E9*(1+Assumptions!F5) -> 16736.928 | G9: =F9*(1+Assumptions!G5) -> 17071.667
A10: Reconciliation | B10: €m | C10: -5966 | D10: =(D8+D9+D11)*Assumptions!D16 -> -5826.8169 | E10: =(E8+E9+E11)*Assumptions!E16 -> -6075.062 | F10: =(F8+F9+F11)*Assumptions!F16 -> -6389.3846 | G10: =(G8+G9+G11)*Assumptions!G16 -> -6713.9364
A11: Financial services revenue | B11: €m | C11: =Historical!E7 -> 24625 | D11: =C11*(1+Assumptions!D7) -> 24625 | E11: =D11*(1+Assumptions!E7) -> 25117.5 | F11: =E11*(1+Assumptions!F7) -> 25871.025 | G11: =F11*(1+Assumptions!G7) -> 26647.156
A12: Total revenue | B12: €m | C12: =Historical!E8 -> 132214 | D12: =SUM(D8:D11) -> 129053.2 | E12: =SUM(E8:E11) -> 134551.37 | F12: =SUM(F8:F11) -> 141513.04 | G12: =SUM(G8:G11) -> 148701.26

Sheet P&L Forecast
A1: Income Statement Forecast | B1: Income Statement Forecast | C1: Income Statement Forecast | D1: Income Statement Forecast | E1: Income Statement Forecast | F1: Income Statement Forecast | G1: Income Statement Forecast
A3: Metric | B3: Unit | C3: 2025A | D3: 2026E | E3: 2027E | F3: 2028E | G3: 2029E
A4: Revenue | B4: €m | C4: =Historical!E8 -> 132214 | D4: ='Operating Model'!D12 -> 129053.2 | E4: ='Operating Model'!E12 -> 134551.37 | F4: ='Operating Model'!F12 -> 141513.04 | G4: ='Operating Model'!G12 -> 148701.26
A5: Gross profit | B5: €m | C5: =Historical!E9 -> 22333 | D5: =D4*Assumptions!D8 -> 22584.311 | E5: =E4*Assumptions!E8 -> 24892.004 | F5: =F4*Assumptions!F8 -> 26887.477 | G5: =G4*Assumptions!G8 -> 28996.745
A6: Gross margin | B6: % | C6: =C5/C4 -> 0.16891555 | D6: =D5/D4 -> 0.175 | E6: =E5/E4 -> 0.185 | F6: =F5/F4 -> 0.19 | G6: =G5/G4 -> 0.195
A7: R&D | B7: €m | C7: =Historical!E10 -> 6055 | D7: =D4*Assumptions!D9 -> 5549.2877 | E7: =E4*Assumptions!E9 -> 5651.1577 | F7: =F4*Assumptions!F9 -> 5802.0345 | G7: =G4*Assumptions!G9 -> 5948.0503
A8: SG&A | B8: €m | C8: =Historical!E11 -> 12195 | D8: =D4*Assumptions!D10 -> 11872.895 | E8: =E4*Assumptions!E10 -> 12109.624 | F8: =F4*Assumptions!F10 -> 12453.147 | G8: =G4*Assumptions!G10 -> 12639.607
A9: Other operating & financial items | B9: €m | C9: 1737 | D9: =D4*Assumptions!D11 -> 1290.532 | E9: =E4*Assumptions!E11 -> 1076.411 | F9: =F4*Assumptions!F11 -> 849.07822 | G9: =G4*Assumptions!G11 -> 743.50629
A10: EBIT | B10: €m | C10: =Historical!E12 -> 5820 | D10: =D5-D7-D8+D9 -> 6452.6602 | E10: =E5-E7-E8+E9 -> 8207.6338 | F10: =F5-F7-F8+F9 -> 9481.3734 | G10: =G5-G7-G8+G9 -> 11152.594
A11: EBIT margin | B11: % | C11: =C10/C4 -> 0.044019544 | D11: =D10/D4 -> 0.05 | E11: =E10/E4 -> 0.061 | F11: =F10/F4 -> 0.067 | G11: =G10/G4 -> 0.075
A12: Tax | B12: €m | C12: =C10*Assumptions!D12 -> 1629.6 | D12: =D10*Assumptions!D12 -> 1806.7448 | E12: =E10*Assumptions!E12 -> 2298.1375 | F12: =F10*Assumptions!F12 -> 2654.7846 | G12: =G10*Assumptions!G12 -> 3122.7264
A13: Net operating profit after tax | B13: €m | C13: =C10-C12 -> 4190.4 | D13: =D10-D12 -> 4645.9153 | E13: =E10-E12 -> 5909.4963 | F13: =F10-F12 -> 6826.5889 | G13: =G10-G12 -> 8029.8679
A14: Net margin proxy | B14: % | C14: =C13/C4 -> 0.031694072 | D14: =D13/D4 -> 0.036 | E14: =E13/E4 -> 0.04392 | F14: =F13/F4 -> 0.04824 | G14: =G13/G4 -> 0.054

Sheet Cash Flow
A1: Free Cash Flow Forecast | B1: Free Cash Flow Forecast | C1: Free Cash Flow Forecast | D1: Free Cash Flow Forecast | E1: Free Cash Flow Forecast | F1: Free Cash Flow Forecast | G1: Free Cash Flow Forecast
A3: Metric | B3: Unit | C3: 2025A | D3: 2026E | E3: 2027E | F3: 2028E | G3: 2029E
A4: NOPAT | B4: €m | C4: ='P&L Forecast'!C13 -> 4190.4 | D4: ='P&L Forecast'!D13 -> 4645.9153 | E4: ='P&L Forecast'!E13 -> 5909.4963 | F4: ='P&L Forecast'!F13 -> 6826.5889 | G4: ='P&L Forecast'!G13 -> 8029.8679
A5: D&A | B5: €m | C5: =Historical!E14 -> 7223 | D5: ='P&L Forecast'!D4*Assumptions!D13 -> 6968.873 | E5: ='P&L Forecast'!E4*Assumptions!E13 -> 7131.2228 | F5: ='P&L Forecast'!F4*Assumptions!F13 -> 7358.6779 | G5: ='P&L Forecast'!G4*Assumptions!G13 -> 7583.7641
A6: Capex | B6: €m | C6: =Historical!E15 -> 9742 | D6: ='P&L Forecast'!D4*Assumptions!D14 -> 9033.7242 | E6: ='P&L Forecast'!E4*Assumptions!E14 -> 8745.8393 | F6: ='P&L Forecast'!F4*Assumptions!F14 -> 8490.7822 | G6: ='P&L Forecast'!G4*Assumptions!G14 -> 8922.0754
A7: Net working capital | B7: €m | C7: =Historical!E16 -> 19234 | D7: ='P&L Forecast'!D4*Assumptions!D15 -> 18712.714 | E7: ='P&L Forecast'!E4*Assumptions!E15 -> 19509.949 | F7: ='P&L Forecast'!F4*Assumptions!F15 -> 20519.39 | G7: ='P&L Forecast'!G4*Assumptions!G15 -> 21561.682
A8: Change in NWC | B8: €m | C8: - | D8: =D7-C7 -> -521.28555 | E8: =E7-D7 -> 797.23465 | F8: =F7-E7 -> 1009.4411 | G8: =G7-F7 -> 1042.2921 | I8: =D7-C7 -> -521.28555
A9: Unlevered FCF | B9: €m | C9: =C4+C5-C6 -> 1671.4 | D9: =D4+D5-D6-D8 -> 3102.3496 | E9: =E4+E5-E6-E8 -> 3497.6452 | F9: =F4+F5-F6-F8 -> 4685.0435 | G9: =G4+G5-G6-G8 -> 5649.2645
A10: FCF margin | B10: % | C10: =C9/'P&L Forecast'!C4 -> 0.012641626 | D10: =D9/'P&L Forecast'!D4 -> 0.024039307 | E10: =E9/'P&L Forecast'!E4 -> 0.025994868 | F10: =F9/'P&L Forecast'!F4 -> 0.033106798 | G10: =G9/'P&L Forecast'!G4 -> 0.037990698
A11: Industrial Business FCF
A12: Bear case FCF | B12: €m | D12: 4500 | E12: 5000 | F12: 5500 | G12: 6000
A13: Base case FCF | B13: €m | C13: 5414 | D13: 5000 | E13: 6000 | F13: 7000 | G13: 7500
A14: Bull case FCF | B14: €m | D14: 5500 | E14: 7000 | F14: 8500 | G14: 9500
A15: FCF Growth | B15: % | D15: =D13/C13-1 -> -0.076468415 | E15: =E13/D13-1 -> 0.2 | F15: =F13/E13-1 -> 0.16666667 | G15: =G13/F13-1 -> 0.071428571
A18: Selected Industrial FCF
D19: =IF(Assumptions!$B$29="Bear",D12,IF(Assumptions!$B$29="Base",D13,D14)) -> 5000 | E19: =IF(Assumptions!$B$29="Bear",E12,IF(Assumptions!$B$29="Base",E13,E14)) -> 6000 | F19: =IF(Assumptions!$B$29="Bear",F12,IF(Assumptions!$B$29="Base",F13,F14)) -> 7000 | G19: =IF(Assumptions!$B$29="Bear",G12,IF(Assumptions!$B$29="Base",G13,G14)) -> 7500

Sheet DCF Valuation
A5: DCF Valuation | B5: DCF Valuation | C5: DCF Valuation | D5: DCF Valuation | E5: DCF Valuation | F5: DCF Valuation | G5: DCF Valuation
A7: Metric | B7: Unit | C7: 2025A | D7: 2026E | E7: 2027E | F7: 2028E | G7: 2029E
A8: Industrial FCF – Valuation Assumption | B8: €m | C8: ='Cash Flow'!C13 -> 5414 | D8: ='Cash Flow'!D19 -> 5000 | E8: ='Cash Flow'!E19 -> 6000 | F8: ='Cash Flow'!F19 -> 7000 | G8: ='Cash Flow'!G19 -> 7500
A9: Discount period | B9: years | C9: 0 | D9: 1 | E9: 2 | F9: 3 | G9: 4
A10: Discount factor | B10: x | C10: - | D10: =1/(1+Assumptions!B19)^D9 -> 0.91324201 | E10: =1/(1+Assumptions!B19)^E9 -> 0.83401097 | F10: =1/(1+Assumptions!$B$19)^F9 -> 0.76165385 | G10: =1/(1+Assumptions!$B$19)^G9 -> 0.69557429
A11: PV of FCF | B11: €m | D11: =D8*D10 -> 4566.21 | E11: =E8*E10 -> 5004.0658 | F11: =F8*F10 -> 5331.577 | G11: =G8*G10 -> 5216.8072
A14: Valuation Bridge | B14: Valuation Bridge | C14: Valuation Bridge | D14: Valuation Bridge
A15: Terminal FCF (€m) | B15: =G8*(1+Assumptions!B26) -> 7650
A16: Terminal value (€m) | B16: =B15/(Assumptions!B19-Assumptions!B26) -> 102000
A17: PV terminal value (€m) | B17: =B16*G10 -> 70948.578 | F17: Financial Services Book Equity | G17: =Assumptions!B32 -> 12053
A18: PV forecast FCF (€m) | B18: =SUM(D11:G11) -> 20118.66 | F18: Financial Services P/B | G18: =Assumptions!B31 -> 1.47
A19: Enterprise value (€m) | B19: =B17+B18 -> 91067.238 | F19: Financial Services Equity Value | G19: =G17*G18 -> 17717.91
A21: Industrial Business Enterprise Value | B21: =B19 -> 91067.238
A22: + Industrial Net Liquidity | B22: =Assumptions!B30 -> 32162
A23: + Financial Services Equity Value | B23: =G19 -> 17717.91
A24: Mercedes-Benz Equity Value | B24: =B21+B22+B23 -> 140947.15
A26: Riga | B26: Valore (€m)
A27: Enterprise Value – Industrial Business | B27: =B17+B18 -> 91067.238
A28: Industrial Net Liquidity | B28: =Assumptions!B30 -> 32162
A29: Financial Services Equity Value | B29: =G19 -> 17717.91
A30: Equity Value | B30: =B27+B28+B29 -> 140947.15
A32: DCF Sensitivity Analysis
A33: Terminal Growth ↓ / WACC → | B33: 0.085 | C33: 0.09 | D33: 0.095 | E33: 0.1 | F33: 0.105
A34: 0.01 | B34: =$D$8/(1+B$33)^1+$E$8/(1+B$33)^2+$F$8/(1+B$33)^3+$G$8/(1+B$33)^4+($G$8*(1+$A34)/(B$33-$A34))/(1+B$33)^4+$B$22+$B$29 -> 143356.1 | C34: =$D$8/(1+C$33)^1+$E$8/(1+C$33)^2+$F$8/(1+C$33)^3+$G$8/(1+C$33)^4+($G$8*(1+$A34)/(C$33-$A34))/(1+C$33)^4+$B$22+$B$29 -> 137314.63 | D34: =$D$8/(1+D$33)^1+$E$8/(1+D$33)^2+$F$8/(1+D$33)^3+$G$8/(1+D$33)^4+($G$8*(1+$A34)/(D$33-$A34))/(1+D$33)^4+$B$22+$B$29 -> 131986.51 | E34: =$D$8/(1+E$33)^1+$E$8/(1+E$33)^2+$F$8/(1+E$33)^3+$G$8/(1+E$33)^4+($G$8*(1+$A34)/(E$33-$A34))/(1+E$33)^4+$B$22+$B$29 -> 127252.81 | F34: =$D$8/(1+F$33)^1+$E$8/(1+F$33)^2+$F$8/(1+F$33)^3+$G$8/(1+F$33)^4+($G$8*(1+$A34)/(F$33-$A34))/(1+F$33)^4+$B$22+$B$29 -> 123019.63
A35: 0.015 | B35: =$D$8/(1+B$33)^1+$E$8/(1+B$33)^2+$F$8/(1+B$33)^3+$G$8/(1+B$33)^4+($G$8*(1+$A35)/(B$33-$A35))/(1+B$33)^4+$B$22+$B$29 -> 148948.3 | C35: =$D$8/(1+C$33)^1+$E$8/(1+C$33)^2+$F$8/(1+C$33)^3+$G$8/(1+C$33)^4+($G$8*(1+$A35)/(C$33-$A35))/(1+C$33)^4+$B$22+$B$29 -> 142140.78 | D35: =$D$8/(1+D$33)^1+$E$8/(1+D$33)^2+$F$8/(1+D$33)^3+$G$8/(1+D$33)^4+($G$8*(1+$A35)/(D$33-$A35))/(1+D$33)^4+$B$22+$B$29 -> 136186.81 | E35: =$D$8/(1+E$33)^1+$E$8/(1+E$33)^2+$F$8/(1+E$33)^3+$G$8/(1+E$33)^4+($G$8*(1+$A35)/(E$33-$A35))/(1+E$33)^4+$B$22+$B$29 -> 130935.73 | F35: =$D$8/(1+F$33)^1+$E$8/(1+F$33)^2+$F$8/(1+F$33)^3+$G$8/(1+F$33)^4+($G$8*(1+$A35)/(F$33-$A35))/(1+F$33)^4+$B$22+$B$29 -> 126270.34
A36: 0.02 | B36: =$D$8/(1+B$33)^1+$E$8/(1+B$33)^2+$F$8/(1+B$33)^3+$G$8/(1+B$33)^4+($G$8*(1+$A36)/(B$33-$A36))/(1+B$33)^4+$B$22+$B$29 -> 155400.84 | C36: =$D$8/(1+C$33)^1+$E$8/(1+C$33)^2+$F$8/(1+C$33)^3+$G$8/(1+C$33)^4+($G$8*(1+$A36)/(C$33-$A36))/(1+C$33)^4+$B$22+$B$29 -> 147656.37 | D36: =$D$8/(1+D$33)^1+$E$8/(1+D$33)^2+$F$8/(1+D$33)^3+$G$8/(1+D$33)^4+($G$8*(1+$A36)/(D$33-$A36))/(1+D$33)^4+$B$22+$B$29 -> 140947.15 | E36: =$D$8/(1+E$33)^1+$E$8/(1+E$33)^2+$F$8/(1+E$33)^3+$G$8/(1+E$33)^4+($G$8*(1+$A36)/(E$33-$A36))/(1+E$33)^4+$B$22+$B$29 -> 135079.01 | F36: =$D$8/(1+F$33)^1+$E$8/(1+F$33)^2+$F$8/(1+F$33)^3+$G$8/(1+F$33)^4+($G$8*(1+$A36)/(F$33-$A36))/(1+F$33)^4+$B$22+$B$29 -> 129903.49
A37: 0.025 | B37: =$D$8/(1+B$33)^1+$E$8/(1+B$33)^2+$F$8/(1+B$33)^3+$G$8/(1+B$33)^4+($G$8*(1+$A37)/(B$33-$A37))/(1+B$33)^4+$B$22+$B$29 -> 162928.81 | C37: =$D$8/(1+C$33)^1+$E$8/(1+C$33)^2+$F$8/(1+C$33)^3+$G$8/(1+C$33)^4+($G$8*(1+$A37)/(C$33-$A37))/(1+C$33)^4+$B$22+$B$29 -> 154020.52 | D37: =$D$8/(1+D$33)^1+$E$8/(1+D$33)^2+$F$8/(1+D$33)^3+$G$8/(1+D$33)^4+($G$8*(1+$A37)/(D$33-$A37))/(1+D$33)^4+$B$22+$B$29 -> 146387.53 | E37: =$D$8/(1+E$33)^1+$E$8/(1+E$33)^2+$F$8/(1+E$33)^3+$G$8/(1+E$33)^4+($G$8*(1+$A37)/(E$33-$A37))/(1+E$33)^4+$B$22+$B$29 -> 139774.73 | F37: =$D$8/(1+F$33)^1+$E$8/(1+F$33)^2+$F$8/(1+F$33)^3+$G$8/(1+F$33)^4+($G$8*(1+$A37)/(F$33-$A37))/(1+F$33)^4+$B$22+$B$29 -> 133990.78
A41: Equity value (€m) | B41: =B30 -> 140947.15 | F41: Valuation | G41: € / Share
A42: Shares Outstanding (m) | B42: =Assumptions!B33 -> 962.904 | F42: Current Price | G42: =B44 -> 41.28
A43: Implied Value per Share (€) | B43: =B41/B42 -> 146.37715 | F43: Low | G43: =F34/$B$42 -> 127.75897
A44: Current Share Price (€) | B44: =Assumptions!B27 -> 41.28 | F44: Base | G44: =D36/$B$42 -> 146.37715
A45: Upside / (Downside) (%) | B45: =B43/B44-1 -> 2.5459582 | F45: High | G45: =B37/$B$42 -> 169.20566

Sheet Dashboard
A1: Mercedes-Benz Financial Model – Valuation Dashboard | B1: Mercedes-Benz Model Dashboard | C1: Mercedes-Benz Model Dashboard | D1: Mercedes-Benz Model Dashboard | E1: Mercedes-Benz Model Dashboard | F1: Mercedes-Benz Model Dashboard | G1: Mercedes-Benz Model Dashboard | H1: Mercedes-Benz Model Dashboard
A3: KPI | B3: Value | D3: 2025A | E3: 2026E | F3: 2027E | G3: 2028E | H3: 2029E | J3: Valuation Range
A4: 2029E Revenue (€m) | B4: ='P&L Forecast'!G4 -> 148701.26 | C4: Revenue (€m) | D4: ='P&L Forecast'!C4 -> 132214 | E4: ='P&L Forecast'!D4 -> 129053.2 | F4: ='P&L Forecast'!E4 -> 134551.37 | G4: ='P&L Forecast'!F4 -> 141513.04 | H4: ='P&L Forecast'!G4 -> 148701.26 | J4: Current Price | K4: ='DCF Valuation'!B44 -> 41.28
A5: 2029E EBIT Margin | B5: ='P&L Forecast'!G11 -> 0.075 | C5: EBIT (€m) | D5: ='P&L Forecast'!C10 -> 5820 | E5: ='P&L Forecast'!D10 -> 6452.6602 | F5: ='P&L Forecast'!E10 -> 8207.6338 | G5: ='P&L Forecast'!F10 -> 9481.3734 | H5: ='P&L Forecast'!G10 -> 11152.594 | J5: Low | K5: ='DCF Valuation'!G43 -> 127.75897
A6: 2029E FCF (€m) | B6: ='Cash Flow'!G9 -> 5649.2645 | C6: FCF (€m) | D6: ='Cash Flow'!C9 -> 1671.4 | E6: ='Cash Flow'!D9 -> 3102.3496 | F6: ='Cash Flow'!E9 -> 3497.6452 | G6: ='Cash Flow'!F9 -> 4685.0435 | H6: ='Cash Flow'!G9 -> 5649.2645 | J6: Base | K6: ='DCF Valuation'!G44 -> 146.37715
A7: Implied Value / Share (€) | B7: ='DCF Valuation'!B43 -> 146.37715 | J7: High | K7: ='DCF Valuation'!G45 -> 169.20566
A8: Upside / (Downside) | B8: ='DCF Valuation'!B45 -> 2.5459582

Sheet Summary
B2: Mercedes-Benz Group – DCF Valuation Summary
B3: Base Case Valuation
A5: Mercedes-Benz Valuation Summary
A6: Selected Scenario | B6: Base
A7: Current Share Price (€) | B7: ='DCF Valuation'!B44 -> 41.28
A8: Implied Value per Share (€) | B8: ='DCF Valuation'!B43 -> 146.37715
A9: Upside / (Downside) | B9: ='DCF Valuation'!B45 -> 2.5459582
A11: Key Assumptions
A14: WACC | B14: =Assumptions!B19 -> 0.095
A15: Terminal Growth Rate | B15: =Assumptions!B26 -> 0.02
A16: Industrial FCF 2029 (€m) | B16: ='Cash Flow'!G19 -> 7500
A17: Financial Services P/B | B17: ='DCF Valuation'!G18 -> 1.47
A21: Valuation Output
A22: Industrial Enterprise Value (€m) | B22: ='DCF Valuation'!B27 -> 91067.238
A23: Industrial Net Liquidity (€m) | B23: ='DCF Valuation'!B28 -> 32162
A24: Financial Services Equity Value (€m) | B24: ='DCF Valuation'!B29 -> 17717.91
A25: Equity Value (€m) | B25: ='DCF Valuation'!B30 -> 140947.15
A26: Shares Outstanding (m) | B26: =Assumptions!B33 -> 962.904
A27: Implied Value per Share (€) | B27: =B25/B26 -> 146.37715
A28: Current Share Price (€) | B28: ='DCF Valuation'!B44 -> 41.28
A29: Upside / (Downside) | B29: =(B27/B28)-1 -> 2.5459582
A31: Valuation Sensitivity
A32: Scenario | B32: WACC | C32: Terminal Growth | D32: Implied Value per Share (€)
A33: Low | B33: =Assumptions!B20 -> 0.105 | C33: =Assumptions!B21 -> 0.01 | D33: ='DCF Valuation'!F34/B26 -> 127.75897
A34: Base | B34: =Assumptions!B19 -> 0.095 | C34: =Assumptions!B26 -> 0.02 | D34: ='DCF Valuation'!D36/B26 -> 146.37715
A35: High | B35: =Assumptions!B22 -> 0.085 | C35: =Assumptions!B23 -> 0.025 | D35: ='DCF Valuation'!B37/B26 -> 169.20566
